[
  {
    "url": "https://www.zhihu.com/question/6477078418",
    "title": "养乐多上海公司解散、工厂停产，它在中国市场的竞争力如何？未来发展策略可能是什么？"
  },
  {
    "url": "https://www.zhihu.com/question/7030717661",
    "title": "2024 乒超联赛樊振东 3:1 战胜王楚钦，如何评价这场比赛？"
  },
  {
    "url": "https://www.zhihu.com/question/263896133",
    "title": "有哪些大家默认「肯定没人能解释清楚」，而实际上已经被科学解释了的问题？"
  },
  {
    "url": "https://www.zhihu.com/question/6902414538",
    "title": "有人分享攻略称，反复评论「机票太贵」让票价便宜 2000 多，如何看待这波操作？算法真能被「驯化」吗？"
  },
  {
    "url": "https://www.zhihu.com/question/6933226018",
    "title": "《明日方舟：终末地》二测版本改了哪些内容？"
  },
  {
    "url": "https://www.zhihu.com/question/6844583681",
    "title": "2024 年最让你难忘的电影电视剧角色是？为什么？"
  },
  {
    "url": "https://www.zhihu.com/question/6732147106",
    "title": "当前环境下，您还会购买纸质书吗？会在什么情况下购买呢？"
  },
  {
    "url": "https://www.zhihu.com/question/5803273094",
    "title": "《我是刑警》中叶茂生之死，是否说明执法过程中一味秉持程序正义变相降低了犯罪成本？"
  },
  {
    "url": "https://www.zhihu.com/question/477254084",
    "title": "玉皇大帝和如来哪一个官职比较大？"
  },
  {
    "url": "https://www.zhihu.com/question/6974968905",
    "title": "媒体曝光「先用后付」套路多，商家可强制扣款，还能逃避国家监管，「先用后付」还存在哪些问题需要警惕？"
  },
  {
    "url": "https://www.zhihu.com/question/6979349938",
    "title": "日本东京将允许政府员工执行「上四休三」工作制，将带来哪些影响？是否会更大范围推广？"
  },
  {
    "url": "https://www.zhihu.com/question/660271372",
    "title": "“哪怕是顶级强者在不使用身体强化类技能的情况下，一个小女孩用刀也能刺伤他的身体”这种设定有什么优缺点？"
  },
  {
    "url": "https://www.zhihu.com/question/6708252798",
    "title": "如果领导在微信上发重要文件，你回复收到却忘记接收，后面想起来已经不能下载，你会怎么办？"
  },
  {
    "url": "https://www.zhihu.com/question/620329076",
    "title": "如何看待《BanG Dream！It's MyGO！！！！！》动画中的长崎爽世？"
  },
  {
    "url": "https://www.zhihu.com/question/6165818169",
    "title": "本田中国 2024 年 11 月终端汽车销量同比下降 30.7%，2025 年它的情况会怎样？"
  },
  {
    "url": "https://www.zhihu.com/question/6980969784",
    "title": "11 月 70 城房价出炉，17 城新房价格环比上涨，各线城市同比降幅今年以来首次均收窄，如何解读？"
  },
  {
    "url": "https://www.zhihu.com/question/6452565879",
    "title": "留学 QS 100/200 名之后的大学还有没有意义？"
  },
  {
    "url": "https://www.zhihu.com/question/316417206",
    "title": "《纯粹理性批判》讲了什么？"
  },
  {
    "url": "https://www.zhihu.com/question/658697566",
    "title": "为什么大多数读者普遍反应网文越来越不好看，而多数作者却仍然觉得网文越来越进步？"
  },
  {
    "url": "https://www.zhihu.com/question/6233097758",
    "title": "曝 V 社正开发 Steam 游戏主机，对此你有哪些期待？"
  },
  {
    "url": "https://www.zhihu.com/question/6980602034",
    "title": "韩国执政党党首韩东勋辞职，会带来哪些影响？国民力量党在韩国政坛还能保持竞争力吗？"
  },
  {
    "url": "https://www.zhihu.com/question/6945962818",
    "title": "如何评价乒超联赛林诗栋 3:2 黄友政？"
  },
  {
    "url": "https://www.zhihu.com/question/6983626474",
    "title": "在 2K 已经是玩家主要分辨率的今天，CPU 到底该怎么选择，才是真正拥有全能持久的沉浸式游戏体验？"
  },
  {
    "url": "https://www.zhihu.com/question/6525588433",
    "title": "当一个优秀员工开始「摆烂」，通常原因是什么呢？"
  },
  {
    "url": "https://www.zhihu.com/question/6912710464",
    "title": "你愿不愿意在大城市过一辈子？"
  },
  {
    "url": "https://www.zhihu.com/question/6482143837",
    "title": "对于即将毕业的国内本科生来说，出国打工是一个好的出路吗?"
  },
  {
    "url": "https://www.zhihu.com/question/6991445743",
    "title": "24-25 赛季NBA常规赛灰熊 110:116 湖人，如何评价这场比赛？"
  },
  {
    "url": "https://www.zhihu.com/question/6640242875",
    "title": "2024年末，你认为游戏本是否需要带「数字小键盘」 ？"
  },
  {
    "url": "https://www.zhihu.com/question/644567760",
    "title": "在整个电子竞技历史上，谁的统治力能比肩当前CSGO的donk？"
  },
  {
    "url": "https://www.zhihu.com/question/6571845691",
    "title": "「朋友圈被领导点赞」成加班证据，公司赔偿 1.8 万，如何界定加班证据？朋友圈点赞能作为合法证据吗？"
  }
]
